[
  {
    "id" :1,
    "imageUrl"  :"/images/market/TopRight.png",
    "name" :"Claynopsaurz",
    "volume" : "200k",
    "price" : "334.1"
  },
  {
    "id" :2,
    "imageUrl"  :"/images/market/TopRight.png",
    "name" :"Claynopsaurz",
    "volume" : "200k",
    "price" : "334.1"
  },
  {
    "id" :3,
    "imageUrl"  :"/images/market/TopRight.png",
    "name" :"Claynopsaurz",
    "volume" : "200k",
    "price" : "334.1"
  },
  {
    "id" :4,
    "imageUrl"  :"/images/market/TopRight.png",
    "name" :"Claynopsaurz",
    "volume" : "200k",
    "price" : "334.1"
  },
  {
    "id" :5,
    "imageUrl"  :"/images/market/TopRight.png",
    "name" :"Claynopsaurz",
    "volume" : "200k",
    "price" : "334.1"
  }
]